odoo/addons/helpdesk_motive/README.rst
odoo/addons/helpdesk_motive/__init__.py
odoo/addons/helpdesk_motive/__manifest__.py
odoo/addons/helpdesk_motive/demo/helpdesk_motive_demo.xml
odoo/addons/helpdesk_motive/i18n/es.po
odoo/addons/helpdesk_motive/i18n/es_AR.po
odoo/addons/helpdesk_motive/i18n/fr.po
odoo/addons/helpdesk_motive/i18n/helpdesk_motive.pot
odoo/addons/helpdesk_motive/i18n/it.po
odoo/addons/helpdesk_motive/i18n/pt.po
odoo/addons/helpdesk_motive/i18n/pt_BR.po
odoo/addons/helpdesk_motive/i18n/sv.po
odoo/addons/helpdesk_motive/models/__init__.py
odoo/addons/helpdesk_motive/models/helpdesk_ticket.py
odoo/addons/helpdesk_motive/models/helpdesk_ticket_motive.py
odoo/addons/helpdesk_motive/models/helpdesk_ticket_team.py
odoo/addons/helpdesk_motive/readme/CONFIGURE.md
odoo/addons/helpdesk_motive/readme/CONTRIBUTORS.md
odoo/addons/helpdesk_motive/readme/DESCRIPTION.md
odoo/addons/helpdesk_motive/readme/USAGE.md
odoo/addons/helpdesk_motive/security/ir.model.access.csv
odoo/addons/helpdesk_motive/static/description/icon.png
odoo/addons/helpdesk_motive/static/description/index.html
odoo/addons/helpdesk_motive/tests/__init__.py
odoo/addons/helpdesk_motive/tests/test_helpdesk_motive.py
odoo/addons/helpdesk_motive/views/helpdesk_ticket.xml
odoo/addons/helpdesk_motive/views/helpdesk_ticket_motive.xml
odoo/addons/helpdesk_motive/views/helpdesk_ticket_team.xml
odoo_addon_helpdesk_motive-18.0.1.0.0.3.dist-info/METADATA
odoo_addon_helpdesk_motive-18.0.1.0.0.3.dist-info/WHEEL
odoo_addon_helpdesk_motive-18.0.1.0.0.3.dist-info/top_level.txt
odoo_addon_helpdesk_motive-18.0.1.0.0.3.dist-info/RECORD
